savedownloadexam/__init__.py
savedownloadexam/savedownloadexam.py
savedownloadexam/set_metadata.py
savedownloadexam_sebastian_stigler-0.0.8.dist-info/LICENSE.txt
savedownloadexam_sebastian_stigler-0.0.8.dist-info/METADATA
savedownloadexam_sebastian_stigler-0.0.8.dist-info/WHEEL
savedownloadexam_sebastian_stigler-0.0.8.dist-info/entry_points.txt
savedownloadexam_sebastian_stigler-0.0.8.dist-info/top_level.txt
savedownloadexam_sebastian_stigler-0.0.8.dist-info/RECORD
