Metadata-Version: 2.1
Name: savedownloadexam-sebastian-stigler
Version: 0.0.8
Summary: Add a short description here!
Home-page: https://in-stigler.htw-aalen.de/gitea/tools/savedownloadexam
Author: Sebastian Stigler
Author-email: sebastian.stigler@hs-aalen.de
License: MIT
Project-URL: Source, https://in-stigler.htw-aalen.de/gitea/tools/savedownloadexam
Platform: any
Classifier: Development Status :: 4 - Beta
Classifier: Programming Language :: Python
License-File: LICENSE.txt
Requires-Dist: ipython (>=7.27.0)
Requires-Dist: ipywidgets (<=7.7.2,>=7.6.5)
Requires-Dist: importlib-metadata ; python_version < "3.8"
Provides-Extra: testing
Requires-Dist: setuptools ; extra == 'testing'
Requires-Dist: pytest ; extra == 'testing'
Requires-Dist: pytest-cov ; extra == 'testing'
